lrmatrix/__init__.py
lrmatrix/explanation.py
lrmatrix/matrixdraw.py
lrmatrix/matrixmanager.py
lrmatrix/rulevectormatrix.py
lrmatrix/treevis.py
lrmatrix-0.1.5.dist-info/LICENSE.txt
lrmatrix-0.1.5.dist-info/METADATA
lrmatrix-0.1.5.dist-info/WHEEL
lrmatrix-0.1.5.dist-info/top_level.txt
lrmatrix-0.1.5.dist-info/RECORD
