Metadata-Version: 2.2
Name: lrmatrix
Version: 0.1.5
Summary: Logic Rules Matrix package to support the ExMatrix and VAX methods.
Home-page: https://gitlab.com/popolinneto/
Author: Mario Popolin Neto
License: Creative Commons Attribution-NonCommercial-ShareAlike 4.0 International
Classifier: License :: Free for non-commercial use
Classifier: Operating System :: OS Independent
Classifier: Programming Language :: Python :: 3
Requires-Python: >=3.6
License-File: LICENSE.txt
Requires-Dist: numpy>=1.19.1
Requires-Dist: matplotlib==3.6.2
Requires-Dist: scikit-learn>=0.23.2
Requires-Dist: drawSvg==1.9.0
Requires-Dist: graphviz>=0.14.1
Requires-Dist: pydotplus>=2.0.2
Dynamic: author
Dynamic: classifier
Dynamic: description
Dynamic: description-content-type
Dynamic: home-page
Dynamic: license
Dynamic: requires-dist
Dynamic: requires-python
Dynamic: summary
